awsenv/__init__.py
awsenv/__main__.py
awsenv/awsenv.py
awsenv_cli-0.0.3.dist-info/LICENSE.txt
awsenv_cli-0.0.3.dist-info/METADATA
awsenv_cli-0.0.3.dist-info/WHEEL
awsenv_cli-0.0.3.dist-info/entry_points.txt
awsenv_cli-0.0.3.dist-info/top_level.txt
awsenv_cli-0.0.3.dist-info/RECORD
