Metadata-Version: 2.1
Name: awsenv-cli
Version: 0.0.3
Summary: Simple CLI to source and cache AWS credentials
Home-page: https://github.com/MohamedKari/awsenv
Author: Mo Kari, Finn Weiler, Luis Falconeri
Author-email: mo@mkari.de
License: UNKNOWN
Project-URL: Bug Tracker, https://github.com/MohamedKari/awsenv/issues
Platform: UNKNOWN
Classifier: Programming Language :: Python :: 3
Classifier: License :: OSI Approved :: MIT License
Classifier: Operating System :: MacOS
Requires-Python: >=3.6
Requires-Dist: boto3
